testcontainers/compose/__init__.py
tests/test_docker_compose.py
testcontainers_compose-0.0.1rc1.dist-info/METADATA
testcontainers_compose-0.0.1rc1.dist-info/WHEEL
testcontainers_compose-0.0.1rc1.dist-info/top_level.txt
testcontainers_compose-0.0.1rc1.dist-info/RECORD
